odoo/addons/website_event_ticket_limit/README.rst
odoo/addons/website_event_ticket_limit/__init__.py
odoo/addons/website_event_ticket_limit/__manifest__.py
odoo/addons/website_event_ticket_limit/i18n/fr.po
odoo/addons/website_event_ticket_limit/i18n/it.po
odoo/addons/website_event_ticket_limit/i18n/website_event_ticket_limit.pot
odoo/addons/website_event_ticket_limit/models/__init__.py
odoo/addons/website_event_ticket_limit/models/event_ticket.py
odoo/addons/website_event_ticket_limit/readme/CONFIGURE.rst
odoo/addons/website_event_ticket_limit/readme/CONTRIBUTORS.rst
odoo/addons/website_event_ticket_limit/readme/CREDITS.rst
odoo/addons/website_event_ticket_limit/readme/DESCRIPTION.rst
odoo/addons/website_event_ticket_limit/static/description/icon.png
odoo/addons/website_event_ticket_limit/static/description/index.html
odoo/addons/website_event_ticket_limit/templates/event_templates_registration.xml
odoo/addons/website_event_ticket_limit/views/event_ticket_views.xml
odoo_addon_website_event_ticket_limit-16.0.1.0.0.6.dist-info/METADATA
odoo_addon_website_event_ticket_limit-16.0.1.0.0.6.dist-info/WHEEL
odoo_addon_website_event_ticket_limit-16.0.1.0.0.6.dist-info/top_level.txt
odoo_addon_website_event_ticket_limit-16.0.1.0.0.6.dist-info/RECORD
